Metadata-Version: 1.0
Name: PyTextSort
Version: 1.0.7
Summary: custom rules to sort a text file
Home-page: https://github.com/djjjj/py-text-sort
Author: djj
Author-email: 510620510@qq.com
License: UNKNOWN
Platform: UNKNOWN
